{
  "templates": {
    "type": "JSON",
    "content": [
      {
        "id": "144988733",
        "Flight": "WS2215",
        "PickupDate": "2025-12-20",
        "PickupTime": "13:45",
        "HotelName": "Delta Hotels by Marriott Riviera Nayarit",
        "HotelNumber": 16705
      },
      {
        "id": "144982713",
        "Flight": "WS2113",
        "PickupDate": "2025-12-20",
        "PickupTime": "08:30",
        "HotelName": "Delta Hotels by Marriott Riviera Nayarit",
        "HotelNumber": 16705
      },
      {
        "id": "148541203",
        "Flight": "WS2181",
        "PickupDate": "2025-12-20",
        "PickupTime": "04:30",
        "HotelName": "Delta Hotels by Marriott Riviera Nayarit",
        "HotelNumber": 16705
      }
    ],
    "source": {
      "data_source": "Google Sheets (Private)",
      "update_frequency": "Automated"
    }
  }
}